perfecto/__init__.py
perfecto/perfectoai.py
perfectoai-1.0.35.dist-info/METADATA
perfectoai-1.0.35.dist-info/WHEEL
perfectoai-1.0.35.dist-info/entry_points.txt
perfectoai-1.0.35.dist-info/top_level.txt
perfectoai-1.0.35.dist-info/RECORD
