Metadata-Version: 2.1
Name: perfectoai
Version: 1.0.35
Summary: PerfectoAI is an automated emailable analytics tool along with AI graphs & predictions
Home-page: UNKNOWN
Author: Genesis Thomas
Author-email: gthomas@perforce.com
License: UNKNOWN
Keywords: Perfecto,appium,selenium,testing,api,automation
Platform: UNKNOWN
Classifier: Programming Language :: Python :: 3
Classifier: Operating System :: OS Independent
Requires-Dist: json2html
Requires-Dist: jenkinsapi
Requires-Dist: requests
Requires-Dist: numpy
Requires-Dist: cython
Requires-Dist: pandas (==1.2.4)
Requires-Dist: retrying
Requires-Dist: ephem
Requires-Dist: pymeeus
Requires-Dist: easydict
Requires-Dist: psutil
Requires-Dist: korean-lunar-calendar
Requires-Dist: MarkupSafe
Requires-Dist: jinja2
Requires-Dist: colorama
Requires-Dist: LunarCalendar
Requires-Dist: holidays
Requires-Dist: cmdstanpy (==0.9.68)
Requires-Dist: convertdate
Requires-Dist: openpyxl
Requires-Dist: wheel
Requires-Dist: pystan (==2.19.1.1)
Requires-Dist: xlrd
Requires-Dist: tzlocal
Requires-Dist: plotly
Requires-Dist: prophet (==1.0.1)
